pintail-0.6-py3.10-nspkg.pth
pintail/docbook.py
pintail/ducktype.py
pintail/git.py
pintail/mallard.py
pintail/pintail-atom.xsl
pintail/pintail-html.xsl
pintail/sample.cfg
pintail/search.py
pintail/site.py
pintail/translation.py
pintail-0.6.data/scripts/pintail
pintail-0.6.dist-info/COPYING
pintail-0.6.dist-info/METADATA
pintail-0.6.dist-info/WHEEL
pintail-0.6.dist-info/namespace_packages.txt
pintail-0.6.dist-info/top_level.txt
pintail-0.6.dist-info/RECORD
