Metadata-Version: 2.1
Name: pintail
Version: 0.6
Summary: Build complete web site from Mallard sources.
Home-page: UNKNOWN
Author: Shaun McCance
Author-email: shaunm@gnome.org
License: GPLv2+
Platform: UNKNOWN
Classifier: Development Status :: 3 - Alpha
Classifier: Environment :: Console
Classifier: Programming Language :: Python :: 3
Classifier: Programming Language :: Python :: 3 :: Only
Classifier: Topic :: Documentation
Classifier: Topic :: Software Development :: Documentation
Classifier: Topic :: Text Processing :: Markup
Classifier: Topic :: Text Processing :: Markup :: XML
Classifier: License :: OSI Approved :: GNU General Public License v2 or later (GPLv2+)
License-File: COPYING
Requires-Dist: lxml
